lexer/__init__.py
lexer/lexer.py
pygments_lexer_petrichorscript-1.0.7.dist-info/LICENSE
pygments_lexer_petrichorscript-1.0.7.dist-info/METADATA
pygments_lexer_petrichorscript-1.0.7.dist-info/WHEEL
pygments_lexer_petrichorscript-1.0.7.dist-info/entry_points.txt
pygments_lexer_petrichorscript-1.0.7.dist-info/top_level.txt
pygments_lexer_petrichorscript-1.0.7.dist-info/RECORD
