Metadata-Version: 2.1
Name: pygments-lexer-petrichorscript
Version: 1.0.7
Summary: Pygments lexer for Petrichor Script.
Author-email: SparkliTwizzl <github@sparklitwizzl.com>
License: Anti-Exploitation License Noncommercial Attribution 1.1
Project-URL: Homepage, https://github.com/sparklitwizzl/pygments-lexer-petrichorscript
Classifier: Programming Language :: Python :: 3
Classifier: License :: Free To Use But Restricted
Classifier: Operating System :: OS Independent
Requires-Python: >=3.12
License-File: LICENSE
Requires-Dist: pygments
